odoo10_addon_purchase_triple_discount-10.0.1.1.0-py2.7-nspkg.pth
odoo/addons/purchase_triple_discount/README.rst
odoo/addons/purchase_triple_discount/__init__.py
odoo/addons/purchase_triple_discount/__manifest__.py
odoo/addons/purchase_triple_discount/models/__init__.py
odoo/addons/purchase_triple_discount/models/account_invoice.py
odoo/addons/purchase_triple_discount/models/purchase_order.py
odoo/addons/purchase_triple_discount/tests/__init__.py
odoo/addons/purchase_triple_discount/tests/test_purchase_discount.py
odoo/addons/purchase_triple_discount/views/purchase_view.xml
odoo10_addon_purchase_triple_discount-10.0.1.1.0.dist-info/DESCRIPTION.rst
odoo10_addon_purchase_triple_discount-10.0.1.1.0.dist-info/METADATA
odoo10_addon_purchase_triple_discount-10.0.1.1.0.dist-info/RECORD
odoo10_addon_purchase_triple_discount-10.0.1.1.0.dist-info/WHEEL
odoo10_addon_purchase_triple_discount-10.0.1.1.0.dist-info/metadata.json
odoo10_addon_purchase_triple_discount-10.0.1.1.0.dist-info/namespace_packages.txt
odoo10_addon_purchase_triple_discount-10.0.1.1.0.dist-info/top_level.txt
